<dc:cover>figures/2018_216.jpg</dc:cover><dc:language>en</dc:language><dc:contributor opf:file-as="Cervone, Einor" opf:role="ctb">Einor Cervone</dc:contributor><dc:contributor opf:file-as="Heinrich, Christoph" opf:role="ctb">Christoph Heinrich</dc:contributor><dc:contributor opf:file-as="Fister, Patricia" opf:role="ctb">Patricia Fister</dc:contributor><dc:contributor opf:file-as="Srikureja, Karuna" opf:role="ctb">Karuna Srikureja</dc:contributor><dc:contributor opf:file-as="Kawao, Tomoko" opf:role="ctb">Tomoko Kawao</dc:contributor><dc:contributor opf:file-as="Berry, Paul" opf:role="ctb">Paul Berry</dc:contributor><dc:contributor opf:file-as="McCormick, Melissa" opf:role="ctb">Melissa McCormick</dc:contributor><dc:contributor opf:file-as="Miller, Alison" opf:role="ctb">Alison Miller</dc:contributor><dc:contributor opf:file-as="Stanley, Amy Beth" opf:role="ctb">Amy Beth Stanley</dc:contributor><dc:contributor opf:file-as="Yonemoto, Marcia A." opf:role="ctb">Marcia A. Yonemoto</dc:contributor><dc:contributor opf:file-as="Fong, Dr. John" opf:role="ctb">Dr. John Fong</dc:contributor><dc:contributor opf:file-as="Graham, Patricia" opf:role="ctb">Patricia Graham</dc:contributor><dc:contributor opf:file-as="Maske, Andrew" opf:role="ctb">Andrew Maske</dc:contributor><dc:publisher>Fong-Johnstone Collection, Denver Art Museum</dc:publisher><dc:rights>© 2023 Denver Art Museum</dc:rights><dc:0>http://localhost:1313/css/epub.css</dc:0>